pianoputer/__init__.py
pianoputer/make_kb_file.py
pianoputer/pianoputer.py
pianoputer/audio_files/bowlStereo_c6.wav
pianoputer/audio_files/bowl_c6.wav
pianoputer/audio_files/piano_c4.wav
pianoputer/keyboards/azerty_typewriter.txt
pianoputer/keyboards/qwerty_piano.txt
pianoputer-2.0.2.dist-info/LICENSE.txt
pianoputer-2.0.2.dist-info/METADATA
pianoputer-2.0.2.dist-info/WHEEL
pianoputer-2.0.2.dist-info/entry_points.txt
pianoputer-2.0.2.dist-info/top_level.txt
pianoputer-2.0.2.dist-info/RECORD
