Metadata-Version: 2.1
Name: pianoputer
Version: 2.0.2
Summary: Use your computer keyboard as a "piano"
Home-page: https://github.com/Zulko/pianoputer
Author: Zulko
Maintainer: Justin Black
License: see LICENSE.txt
Keywords: piano,keyboard,synthesizer,instrument,music
Platform: UNKNOWN
Classifier: Programming Language :: Python
Classifier: Programming Language :: Python :: 3
Classifier: Intended Audience :: End Users/Desktop
Classifier: Intended Audience :: Education
Classifier: Operating System :: Microsoft :: Windows
Classifier: Operating System :: POSIX
Classifier: Operating System :: MacOS
Classifier: Topic :: Software Development :: Libraries :: Python Modules
Classifier: Topic :: Games/Entertainment :: Simulation
Classifier: Topic :: Multimedia :: Sound/Audio
Classifier: Topic :: Multimedia :: Sound/Audio :: Players
Requires-Python: >=3
Requires-Dist: librosa (>=0.8.0)
Requires-Dist: pygame (>=2.0.0)
Requires-Dist: keyboardlayout (>=2.0.1)
Provides-Extra: dev
Requires-Dist: setuptools ; extra == 'dev'
Requires-Dist: wheel ; extra == 'dev'
Requires-Dist: twine ; extra == 'dev'
Requires-Dist: isort ; extra == 'dev'
Requires-Dist: black ; extra == 'dev'
